extrude/__init__.py
extrude/crude.py
extrude-0.0.3.dist-info/LICENSE
extrude-0.0.3.dist-info/METADATA
extrude-0.0.3.dist-info/WHEEL
extrude-0.0.3.dist-info/top_level.txt
extrude-0.0.3.dist-info/RECORD
