Metadata-Version: 2.1
Name: extrude
Version: 0.0.3
Summary: Tool to run a composite web application to easily interact with python functions
Home-page: https://github.com/i2mint/extrude
Author: OtoSense
License: apache-2.0
Platform: any
License-File: LICENSE
